dukpy/__init__.py
dukpy/_dukpy.cp35-win32.pyd
dukpy/babel-4.6.6.min.js
dukpy/babel.py
dukpy/coffee.py
dukpy/coffeescript.js
dukpy/evaljs.py
dukpy/tsc.py
dukpy/typescriptServices.js
dukpy_lukegb-0.2.1.dist-info/DESCRIPTION.rst
dukpy_lukegb-0.2.1.dist-info/METADATA
dukpy_lukegb-0.2.1.dist-info/RECORD
dukpy_lukegb-0.2.1.dist-info/WHEEL
dukpy_lukegb-0.2.1.dist-info/metadata.json
dukpy_lukegb-0.2.1.dist-info/top_level.txt
