Metadata-Version: 2.0
Name: dukpy-lukegb
Version: 0.2.1
Summary: Simple JavaScript interpreter for Python
Home-page: https://github.com/lukegb/dukpy
Author: Luke Granger-Brown & Alessandro Molina
Author-email: python@lukegb.com
License: MIT
Keywords: javascript compiler babeljs coffeescript
Platform: UNKNOWN
Classifier: Development Status :: 3 - Alpha
Classifier: License :: OSI Approved :: MIT License
Classifier: Programming Language :: Python :: 3.5
Classifier: Programming Language :: Python :: 3.4
Classifier: Programming Language :: Python :: 3.3
Classifier: Programming Language :: Python :: 2.7
Classifier: Programming Language :: JavaScript
